yaml_pyconf/__init__.py
yaml_pyconf/base.py
yaml_pyconf/flask.py
yaml_pyconf/simple.py
yaml_pyconf/samples/sample-dotenv/.env
yaml_pyconf/samples/sample-yaml/flask-choose-env.yaml
yaml_pyconf/samples/sample-yaml/simple.yaml
yaml_pyconf-0.0.3.dist-info/LICENSE
yaml_pyconf-0.0.3.dist-info/METADATA
yaml_pyconf-0.0.3.dist-info/WHEEL
yaml_pyconf-0.0.3.dist-info/top_level.txt
yaml_pyconf-0.0.3.dist-info/RECORD
