Metadata-Version: 2.1
Name: yaml-pyconf
Version: 0.0.3
Summary: Turn YAML files into python objects
Home-page: https://github.com/gabriellesw/yaml-pyconf
Author: Gabrielle Sloane Law
Author-email: rockymcrockerson@gmail.com
License: UNKNOWN
Platform: UNKNOWN
Classifier: Programming Language :: Python :: 3
Classifier: License :: OSI Approved :: MIT License
Classifier: Operating System :: Unix
Classifier: Topic :: Utilities
Classifier: Development Status :: 4 - Beta
Requires-Python: >=3.6
Requires-Dist: python-dotenv
Requires-Dist: PyYAML
